LICENSE
MANIFEST.in
README.md
setup.py
src/sinopy/__init__.py
src/sinopy/characters.py
src/sinopy/cli.py
src/sinopy/data.py
src/sinopy/segmentize.py
src/sinopy/segments.py
src/sinopy/sinopy.py
src/sinopy.egg-info/PKG-INFO
src/sinopy.egg-info/SOURCES.txt
src/sinopy.egg-info/dependency_links.txt
src/sinopy.egg-info/entry_points.txt
src/sinopy.egg-info/not-zip-safe
src/sinopy.egg-info/requires.txt
src/sinopy.egg-info/top_level.txt
src/sinopy/data/README.md
src/sinopy/data/Unihan_Readings.txt
src/sinopy/data/_big5.bin
src/sinopy/data/_gbk.bin
src/sinopy/data/_guangyun.bin
src/sinopy/data/_ids.bin
src/sinopy/data/_tls.bin
src/sinopy/data/_unihan.bin
src/sinopy/data/chinese.json
src/sinopy/data/chinese.tsv
src/sinopy/data/ids-analysis.txt
src/sinopy/data/ids.txt
src/sinopy/data/ids.xlsx
src/sinopy/data/tls.json
src/sinopy/data/wang1980.tsv
src/sinopy/data/yinku.qlc
src/sinopy/data/yiti.tsv
src/sinopy/data/models/arti/INFO
src/sinopy/data/models/arti/converter
src/sinopy/data/models/color/INFO
src/sinopy/data/models/color/converter
src/sinopy/data/models/color/converter.bin
src/sinopy/data/models/dvt/diacritics
src/sinopy/data/models/dvt/tones
src/sinopy/data/models/dvt/vowels
src/sinopy/data/models/sca/INFO
src/sinopy/data/models/sca/converter
src/sinopy/data/models/sca/matrix
src/sinopy/data/models/sca/scorer
src/sinopy/data/profiles/mch.prf
src/sinopy/tests/orthography.ods
src/sinopy/tests/orthography.tsv
src/sinopy/tests/test_data.py
src/sinopy/tests/test_segments.py