Metadata-Version: 2.1
Name: sinopy
Version: 0.3.4
Summary: A Python library for quantitative tasks in Chinese historical linguistics.
Home-page: https://github.com/lingpy/sinopy
Author: Johann-Mattis List
Author-email: list@shh.mpg.de
License: GPL
Keywords: Chinese linguistics,historical linguistics,computer-assisted language comparison
Platform: UNKNOWN
